octopus/__init__.py
octopus/__main__.py
octopus/console.py
octopus/constants.py
octopus/events.py
octopus/queue.py
octopus/util.py
octopus/data/__init__.py
octopus/data/control.py
octopus/data/data.py
octopus/data/errors.py
octopus/data/manipulation.py
octopus/image/__init__.py
octopus/image/blobmaker.py
octopus/image/data.py
octopus/image/functions.py
octopus/image/machine.py
octopus/image/provider.py
octopus/image/source.py
octopus/image/tracker.py
octopus/machine/__init__.py
octopus/machine/interface.py
octopus/machine/machine.py
octopus/manufacturer/__init__.py
octopus/manufacturer/aquila.py
octopus/manufacturer/bronkhorst.py
octopus/manufacturer/dummy.py
octopus/manufacturer/harvard.py
octopus/manufacturer/heidolph.py
octopus/manufacturer/hiteczang.py
octopus/manufacturer/huber.py
octopus/manufacturer/ika.py
octopus/manufacturer/julabo.py
octopus/manufacturer/kern.py
octopus/manufacturer/knauer.py
octopus/manufacturer/mt.py
octopus/manufacturer/omega.py
octopus/manufacturer/sartorious.py
octopus/manufacturer/startech.py
octopus/manufacturer/thalesnano.py
octopus/manufacturer/vapourtec.py
octopus/manufacturer/vici.py
octopus/manufacturer/wpi.py
octopus/notifier/__init__.py
octopus/notifier/sms.py
octopus/protocol/__init__.py
octopus/protocol/basic.py
octopus/protocol/gsioc.py
octopus/sequence/__init__.py
octopus/sequence/control.py
octopus/sequence/error.py
octopus/sequence/experiment.py
octopus/sequence/runtime.py
octopus/sequence/sequence.py
octopus/sequence/shortcuts.py
octopus/sequence/util.py
octopus/transport/__init__.py
octopus/transport/basic.py
octopus/transport/gsioc.py
congo_lab-0.8.0.dist-info/LICENSE
congo_lab-0.8.0.dist-info/METADATA
congo_lab-0.8.0.dist-info/WHEEL
congo_lab-0.8.0.dist-info/top_level.txt
congo_lab-0.8.0.dist-info/RECORD
